verbose_http_exceptions-3.0.0.dist-info/METADATA
verbose_http_exceptions-3.0.0.dist-info/WHEEL
verbose_http_exceptions-3.0.0.dist-info/licenses/LICENSE
verbose_http_exceptions/__init__.py
verbose_http_exceptions/exc/__init__.py
verbose_http_exceptions/exc/base.py
verbose_http_exceptions/exc/client_error.py
verbose_http_exceptions/exc/informational.py
verbose_http_exceptions/exc/nested.py
verbose_http_exceptions/exc/redirection.py
verbose_http_exceptions/exc/server_error.py
verbose_http_exceptions/exc/successful.py
verbose_http_exceptions/ext/__init__.py
verbose_http_exceptions/ext/fastapi/__init__.py
verbose_http_exceptions/ext/fastapi/appliers.py
verbose_http_exceptions/ext/fastapi/constants.py
verbose_http_exceptions/ext/fastapi/exc.py
verbose_http_exceptions/ext/fastapi/handlers.py
verbose_http_exceptions/ext/fastapi/middlewares.py
verbose_http_exceptions/ext/fastapi/openapi_override.py
verbose_http_exceptions/ext/fastapi/utils.py
verbose_http_exceptions/ext/litestar/__init__.py
verbose_http_exceptions/ext/litestar/constants.py
verbose_http_exceptions/ext/litestar/exc.py
verbose_http_exceptions/ext/litestar/handlers.py
verbose_http_exceptions/ext/litestar/mappers.py
verbose_http_exceptions/ext/litestar/types.py
verbose_http_exceptions/ext/litestar/utils.py
verbose_http_exceptions/ext/pydantic_schemas.py
verbose_http_exceptions/py.typed
verbose_http_exceptions/status.py
verbose_http_exceptions/warns.py
verbose_http_exceptions-3.0.0.dist-info/RECORD
