Metadata-Version: 2.1
Name: verbose_http_exceptions
Version: 3.0.0
Summary: Verbose HTTP exceptions package for web frameworks.
Author-Email: Dmitriy Lunev <dima.lunev14@gmail.com>
License: MIT
Requires-Python: >=3.11
Requires-Dist: python-dev-utils==7.0.1
Requires-Dist: fastapi; extra == "fastapi"
Requires-Dist: litestar; extra == "litestar"
Provides-Extra: fastapi
Provides-Extra: litestar
